requirements.txt
setup.py
github_octolytics/__init__.py
github_octolytics.egg-info/PKG-INFO
github_octolytics.egg-info/SOURCES.txt
github_octolytics.egg-info/dependency_links.txt
github_octolytics.egg-info/requires.txt
github_octolytics.egg-info/top_level.txt