Metadata-Version: 2.1
Name: github-octolytics
Version: 2020.7.1
Summary: github octolytics parser
Home-page: https://github.com/andrewp-as-is/github-octolytics.py
License: Unlicense
Keywords: github octolytics
Platform: UNKNOWN
Classifier: License :: Public Domain
Classifier: Operating System :: OS Independent
Classifier: Programming Language :: Python :: 3
